{
  "display": {
    "icon": {
      "id": "minecraft:jukebox"
    },
    "title": {
      "translate": "advancement.jojosquared.silly"
    },
    "description": {
      "translate": "advancement.jojosquared.silly.description"
    },
    "frame": "task",
    "show_toast": true,
    "announce_to_chat": true,
    "hidden": true
  },
  "parent": "jojosquared:hard",
  "criteria": {
    "jukebox": {
      "conditions": {
        "location": [
          {
            "condition": "minecraft:location_check",
            "predicate": {
              "block": {
                "blocks": "minecraft:jukebox"
              }
            }
          },
          {
            "condition": "minecraft:entity_properties",
            "entity": "this",
            "predicate": {
              "items": "jojosquared:stand_disc",
              "equipment": {
                "mainhand": {
                  "items": "jojosquared:stand_disc"
                }
              }
            }
          }
        ]
      },
      "trigger": "minecraft:item_used_on_block"
    }
  }
}

